Metadata-Version: 2.1
Name: searchenginepy
Version: 0.1.5
Summary: Query popular search engines and get results easily
Home-page: https://github.com/codewithnick/searchengine
Download-URL: https://github.com/user/reponame/archive/v_01.tar.gz
Author: codewithnick
Author-email: nikhilsingh52645@gmail.com
License: MIT
Keywords: google,bing,brave,duckduckgo,search engine,crawler
Classifier: Development Status :: 3 - Alpha
Classifier: Intended Audience :: Developers
Classifier: Topic :: Software Development :: Build Tools
Classifier: License :: OSI Approved :: MIT License
Classifier: Programming Language :: Python :: 3
Classifier: Programming Language :: Python :: 3.4
Classifier: Programming Language :: Python :: 3.5
Classifier: Programming Language :: Python :: 3.6
License-File: LICENSE
